Aquarius-0.1.dist-info/DESCRIPTION.rst
Aquarius-0.1.dist-info/METADATA
Aquarius-0.1.dist-info/RECORD
Aquarius-0.1.dist-info/WHEEL
Aquarius-0.1.dist-info/entry_points.txt
Aquarius-0.1.dist-info/metadata.json
Aquarius-0.1.dist-info/top_level.txt
aquarius/__init__.py
aquarius/test/__init__.py
