Metadata-Version: 2.0
Name: Aquarius
Version: 0.1
Summary: Aquarium IoT
Home-page: https://bitbucket.org/uilianries/aquarius
Author: Uilian Ries
Author-email: uilianries@gmail.com
License: MIT
Keywords: iot aquarium fishkeeping
Platform: UNKNOWN
Classifier: Development Status :: 1 - Planning
Classifier: Environment :: Console
Classifier: Intended Audience :: Customer Service
Classifier: Topic :: System :: Networking :: Monitoring
Classifier: License :: OSI Approved :: MIT License
Classifier: Natural Language :: English
Classifier: Operating System :: POSIX :: Linux
Classifier: Programming Language :: Python :: 2
Classifier: Programming Language :: Python :: 2.6
Classifier: Programming Language :: Python :: 2.7
Classifier: Programming Language :: Python :: 3
Classifier: Programming Language :: Python :: 3.2
Classifier: Programming Language :: Python :: 3.3
Classifier: Programming Language :: Python :: 3.4
Requires-Dist: paho-mqtt
Provides-Extra: dev
Requires-Dist: check-manifest; extra == 'dev'
Requires-Dist: pylint; extra == 'dev'
Requires-Dist: yapf; extra == 'dev'
Provides-Extra: test
Requires-Dist: coverage; extra == 'test'
Requires-Dist: pytest; extra == 'test'
